CouchbaseLibrary.py
robotframework_couchbaselibrary-2.0.2.dist-info/LICENSE
robotframework_couchbaselibrary-2.0.2.dist-info/METADATA
robotframework_couchbaselibrary-2.0.2.dist-info/WHEEL
robotframework_couchbaselibrary-2.0.2.dist-info/top_level.txt
robotframework_couchbaselibrary-2.0.2.dist-info/RECORD
