Metadata-Version: 2.1
Name: robotframework-couchbaselibrary
Version: 2.0.2
Summary: A Robot Framework library to work with Couchbase
Home-page: https://github.com/peterservice-rnd/robotframework-couchbaselibrary
Author: JSC PETER-SERVICE
Author-email: mf_aist_all@billing.ru
License: Apache License, Version 2.0
Keywords: testing robotframework couchbase
Platform: UNKNOWN
Classifier: Development Status :: 5 - Production/Stable
Classifier: Intended Audience :: Developers
Classifier: Topic :: Software Development :: Testing
Classifier: License :: OSI Approved :: Apache Software License
Classifier: Programming Language :: Python :: 3.5
Classifier: Programming Language :: Python :: 3.6
Classifier: Framework :: Robot Framework :: Library
Requires-Dist: couchbase (<=2.3.5)
Requires-Dist: robotframework (>=3.0.1)
Requires-Dist: robotframework-jsonvalidator (>=1.0.0)
